<?xml version="1.0" encoding="UTF-8" standalone="yes"?>
<p:sldLayout xmlns:a="http://schemas.openxmlformats.org/drawingml/2006/main" xmlns:r="http://schemas.openxmlformats.org/officeDocument/2006/relationships" xmlns:p="http://schemas.openxmlformats.org/presentationml/2006/main" preserve="1" userDrawn="1"><p:cSld name="Cover Letter"><p:spTree><p:nvGrpSpPr><p:cNvPr id="1" name=""/><p:cNvGrpSpPr/><p:nvPr/></p:nvGrpSpPr><p:grpSpPr><a:xfrm><a:off x="0" y="0"/><a:ext cx="0" cy="0"/><a:chOff x="0" y="0"/><a:chExt cx="0" cy="0"/></a:xfrm></p:grpSpPr><p:sp><p:nvSpPr><p:cNvPr id="6" name="HeaderTOCPlaceholder"><a:extLst><a:ext uri="{FF2B5EF4-FFF2-40B4-BE49-F238E27FC236}"><a16:creationId xmlns:a16="http://schemas.microsoft.com/office/drawing/2014/main" id="{3BD7A876-9A84-4A34-A9D7-BCB2371BCCEF}"/></a:ext></a:extLst></p:cNvPr><p:cNvSpPr/><p:nvPr userDrawn="1"><p:custDataLst><p:tags r:id="rId1"/></p:custDataLst></p:nvPr></p:nvSpPr><p:spPr><a:xfrm><a:off x="3660198" y="322256"/><a:ext cx="5943600" cy="137160"/></a:xfrm><a:prstGeom prst="rect"><a:avLst/></a:prstGeom><a:noFill/></p:spPr><p:txBody><a:bodyPr wrap="square" lIns="0" tIns="0" rIns="0" bIns="0" rtlCol="0" anchor="b" anchorCtr="0"><a:noAutofit/></a:bodyPr><a:lstStyle/><a:p><a:pPr lvl="0"/><a:endParaRPr lang="en-GB" sz="800" dirty="0"/></a:p></p:txBody></p:sp><p:sp><p:nvSpPr><p:cNvPr id="19" name="Side Banner"><a:extLst><a:ext uri="{FF2B5EF4-FFF2-40B4-BE49-F238E27FC236}"><a16:creationId xmlns:a16="http://schemas.microsoft.com/office/drawing/2014/main" id="{6671683F-2826-44A0-B5A0-9FF0E572F5E9}"/></a:ext></a:extLst></p:cNvPr><p:cNvSpPr/><p:nvPr userDrawn="1"/></p:nvSpPr><p:spPr><a:xfrm><a:off x="-2598" y="0"/><a:ext cx="3063240" cy="7772400"/></a:xfrm><a:prstGeom prst="rect"><a:avLst/></a:prstGeom><a:solidFill><a:srgbClr val="DEDEDE"/></a:solidFill><a:ln w="6350"><a:noFill/></a:ln></p:spPr><p:txBody><a:bodyPr rot="0" spcFirstLastPara="0" vertOverflow="overflow" horzOverflow="overflow" vert="horz" wrap="square" lIns="91440" tIns="45720" rIns="91440" bIns="45720" numCol="1" spcCol="0" rtlCol="0" fromWordArt="0" anchor="ctr" anchorCtr="0" forceAA="0" compatLnSpc="1"><a:prstTxWarp prst="textNoShape"><a:avLst/></a:prstTxWarp><a:noAutofit/></a:bodyPr><a:lstStyle/><a:p><a:pPr algn="ctr"/><a:endParaRPr lang="en-GB" dirty="0"/></a:p></p:txBody></p:sp><p:pic><p:nvPicPr><p:cNvPr id="12" name="Logo"><a:extLst><a:ext uri="{FF2B5EF4-FFF2-40B4-BE49-F238E27FC236}"><a16:creationId xmlns:a16="http://schemas.microsoft.com/office/drawing/2014/main" id="{FD426CA0-C22E-455E-A0BC-1B853DA062E5}"/></a:ext></a:extLst></p:cNvPr><p:cNvPicPr><a:picLocks noChangeAspect="1"/></p:cNvPicPr><p:nvPr userDrawn="1"/></p:nvPicPr><p:blipFill><a:blip r:embed="rId9"/><a:stretch><a:fillRect/></a:stretch></p:blipFill><p:spPr bwMode="gray"><a:xfrm><a:off x="221285" y="539958"/><a:ext cx="1800454" cy="1531343"/></a:xfrm><a:prstGeom prst="rect"><a:avLst/></a:prstGeom></p:spPr></p:pic><p:sp><p:nvSpPr><p:cNvPr id="14" name="Text Placeholder 13"><a:extLst><a:ext uri="{FF2B5EF4-FFF2-40B4-BE49-F238E27FC236}"><a16:creationId xmlns:a16="http://schemas.microsoft.com/office/drawing/2014/main" id="{C9037364-9F8A-46ED-9DE8-8FD2CEC2375E}"/></a:ext></a:extLst></p:cNvPr><p:cNvSpPr><a:spLocks noGrp="1"/></p:cNvSpPr><p:nvPr><p:ph type="body" sz="quarter" idx="13" hasCustomPrompt="1"/></p:nvPr></p:nvSpPr><p:spPr><a:xfrm><a:off x="3403600" y="758825"/><a:ext cx="2651760" cy="1097182"/></a:xfrm></p:spPr><p:txBody><a:bodyPr anchor="b"/><a:lstStyle><a:lvl1pPr><a:spcAft><a:spcPts val="0"/></a:spcAft><a:defRPr/></a:lvl1pPr></a:lstStyle><a:p><a:pPr lvl="0"/><a:r><a:rPr lang="en-GB" dirty="0"/><a:t>Insert text here </a:t></a:r></a:p></p:txBody></p:sp><p:sp><p:nvSpPr><p:cNvPr id="16" name="Text Placeholder 15"><a:extLst><a:ext uri="{FF2B5EF4-FFF2-40B4-BE49-F238E27FC236}"><a16:creationId xmlns:a16="http://schemas.microsoft.com/office/drawing/2014/main" id="{41F3A121-5BDD-4494-81E2-8D2802D7A392}"/></a:ext></a:extLst></p:cNvPr><p:cNvSpPr><a:spLocks noGrp="1"/></p:cNvSpPr><p:nvPr><p:ph type="body" sz="quarter" idx="14" hasCustomPrompt="1"/></p:nvPr></p:nvSpPr><p:spPr><a:xfrm><a:off x="457200" y="2143125"/><a:ext cx="2295144" cy="169277"/></a:xfrm></p:spPr><p:txBody><a:bodyPr><a:spAutoFit/></a:bodyPr><a:lstStyle><a:lvl1pPr><a:spcAft><a:spcPts val="0"/></a:spcAft><a:defRPr/></a:lvl1pPr></a:lstStyle><a:p><a:pPr lvl="0"/><a:r><a:rPr lang="en-GB" dirty="0"/><a:t>Insert text here </a:t></a:r></a:p></p:txBody></p:sp><p:sp><p:nvSpPr><p:cNvPr id="18" name="Text Placeholder 17"><a:extLst><a:ext uri="{FF2B5EF4-FFF2-40B4-BE49-F238E27FC236}"><a16:creationId xmlns:a16="http://schemas.microsoft.com/office/drawing/2014/main" id="{16D18B74-4DFB-4B98-9418-E6F37191115A}"/></a:ext></a:extLst></p:cNvPr><p:cNvSpPr><a:spLocks noGrp="1"/></p:cNvSpPr><p:nvPr><p:ph type="body" sz="quarter" idx="15" hasCustomPrompt="1"/></p:nvPr></p:nvSpPr><p:spPr><a:xfrm><a:off x="457200" y="6275937"/><a:ext cx="2295144" cy="169278"/></a:xfrm></p:spPr><p:txBody><a:bodyPr anchor="b"/><a:lstStyle><a:lvl1pPr><a:spcAft><a:spcPts val="0"/></a:spcAft><a:defRPr sz="1000"/></a:lvl1pPr></a:lstStyle><a:p><a:pPr lvl="0"/><a:r><a:rPr lang="en-GB" dirty="0"/><a:t>Address placeholder </a:t></a:r></a:p></p:txBody></p:sp><p:sp><p:nvSpPr><p:cNvPr id="21" name="Text Placeholder 20"><a:extLst><a:ext uri="{FF2B5EF4-FFF2-40B4-BE49-F238E27FC236}"><a16:creationId xmlns:a16="http://schemas.microsoft.com/office/drawing/2014/main" id="{EE7C08EC-15CD-4E5F-BC71-278D937BF715}"/></a:ext></a:extLst></p:cNvPr><p:cNvSpPr><a:spLocks noGrp="1"/></p:cNvSpPr><p:nvPr><p:ph type="body" sz="quarter" idx="16" hasCustomPrompt="1"/></p:nvPr></p:nvSpPr><p:spPr><a:xfrm><a:off x="3403600" y="2143125"/><a:ext cx="6197600" cy="4302090"/></a:xfrm></p:spPr><p:txBody><a:bodyPr/><a:lstStyle><a:lvl1pPr><a:defRPr/></a:lvl1pPr></a:lstStyle><a:p><a:pPr lvl="0"/><a:r><a:rPr lang="en-GB" dirty="0"/><a:t>Insert text here </a:t></a:r></a:p></p:txBody></p:sp><p:sp><p:nvSpPr><p:cNvPr id="23" name="Text Placeholder 22"><a:extLst><a:ext uri="{FF2B5EF4-FFF2-40B4-BE49-F238E27FC236}"><a16:creationId xmlns:a16="http://schemas.microsoft.com/office/drawing/2014/main" id="{E25E6804-9EBD-45CC-A6A7-6FCBBD811662}"/></a:ext></a:extLst></p:cNvPr><p:cNvSpPr><a:spLocks noGrp="1"/></p:cNvSpPr><p:nvPr><p:ph type="body" sz="quarter" idx="17"/></p:nvPr></p:nvSpPr><p:spPr><a:xfrm><a:off x="3403600" y="6584373"/><a:ext cx="6197600" cy="467302"/></a:xfrm></p:spPr><p:txBody><a:bodyPr vert="horz" lIns="0" tIns="0" rIns="0" bIns="0" rtlCol="0" anchor="b" anchorCtr="0"><a:noAutofit/></a:bodyPr><a:lstStyle><a:lvl1pPr><a:spcAft><a:spcPts val="0"/></a:spcAft><a:defRPr lang="en-US" sz="800" smtClean="0"><a:solidFill><a:schemeClr val="bg1"><a:lumMod val="50000"/></a:schemeClr></a:solidFill></a:defRPr></a:lvl1pPr><a:lvl2pPr><a:defRPr lang="en-US" smtClean="0"/></a:lvl2pPr><a:lvl3pPr><a:defRPr lang="en-US" smtClean="0"/></a:lvl3pPr><a:lvl4pPr><a:defRPr lang="en-US" smtClean="0"/></a:lvl4pPr><a:lvl5pPr><a:defRPr lang="en-US"/></a:lvl5pPr></a:lstStyle><a:p><a:pPr lvl="0" defTabSz="1019175"/><a:r><a:rPr lang="en-GB" dirty="0"/><a:t>Click to edit Master text styles</a:t></a:r></a:p></p:txBody></p:sp><p:sp><p:nvSpPr><p:cNvPr id="17" name="Section Footer"><a:extLst><a:ext uri="{FF2B5EF4-FFF2-40B4-BE49-F238E27FC236}"><a16:creationId xmlns:a16="http://schemas.microsoft.com/office/drawing/2014/main" id="{C7AA6082-33D7-4584-9910-D6205D7636A0}"/></a:ext></a:extLst></p:cNvPr><p:cNvSpPr txBox="1"/><p:nvPr userDrawn="1"><p:custDataLst><p:tags r:id="rId2"/></p:custDataLst></p:nvPr></p:nvSpPr><p:spPr><a:xfrm><a:off x="457200" y="7194414"/><a:ext cx="2944368" cy="123111"/></a:xfrm><a:prstGeom prst="rect"><a:avLst/></a:prstGeom><a:noFill/><a:ln><a:noFill/></a:ln></p:spPr><p:txBody><a:bodyPr wrap="square" lIns="0" tIns="0" rIns="0" bIns="0" rtlCol="0" anchor="b" anchorCtr="0"><a:spAutoFit/></a:bodyPr><a:lstStyle/><a:p><a:r><a:rPr lang="en-GB" sz="800" noProof="1"><a:solidFill><a:schemeClr val="tx1"/></a:solidFill><a:latin typeface="Arial" panose="020B0604020202020204" pitchFamily="34" charset="0"/><a:cs typeface="Arial" panose="020B0604020202020204" pitchFamily="34" charset="0"/></a:rPr><a:t>Project Phishing </a:t></a:r></a:p></p:txBody></p:sp><p:sp><p:nvSpPr><p:cNvPr id="26" name="Presentation Disclaimer"><a:extLst><a:ext uri="{FF2B5EF4-FFF2-40B4-BE49-F238E27FC236}"><a16:creationId xmlns:a16="http://schemas.microsoft.com/office/drawing/2014/main" id="{CCC4804F-856D-41FD-9A70-CB75E117EAB2}"/></a:ext></a:extLst></p:cNvPr><p:cNvSpPr txBox="1"/><p:nvPr userDrawn="1"><p:custDataLst><p:tags r:id="rId3"/></p:custDataLst></p:nvPr></p:nvSpPr><p:spPr><a:xfrm><a:off x="4096341" y="7194414"/><a:ext cx="1399422" cy="123111"/></a:xfrm><a:prstGeom prst="rect"><a:avLst/></a:prstGeom><a:noFill/></p:spPr><p:txBody><a:bodyPr wrap="none" lIns="0" tIns="0" rIns="0" bIns="0" rtlCol="0" anchor="t" anchorCtr="0"><a:spAutoFit/></a:bodyPr><a:lstStyle/><a:p><a:pPr algn="l"/><a:r><a:rPr lang="en-GB" sz="800" noProof="1"><a:solidFill><a:schemeClr val="tx1"/></a:solidFill></a:rPr><a:t>Strictly private and confidential</a:t></a:r></a:p></p:txBody></p:sp><p:sp><p:nvSpPr><p:cNvPr id="28" name="Report Date"><a:extLst><a:ext uri="{FF2B5EF4-FFF2-40B4-BE49-F238E27FC236}"><a16:creationId xmlns:a16="http://schemas.microsoft.com/office/drawing/2014/main" id="{BA2C08DE-C36A-401F-A8C1-375711A2A800}"/></a:ext></a:extLst></p:cNvPr><p:cNvSpPr txBox="1"/><p:nvPr userDrawn="1"><p:custDataLst><p:tags r:id="rId4"/></p:custDataLst></p:nvPr></p:nvSpPr><p:spPr><a:xfrm><a:off x="8830155" y="7194414"/><a:ext cx="771045" cy="123111"/></a:xfrm><a:prstGeom prst="rect"><a:avLst/></a:prstGeom><a:noFill/></p:spPr><p:txBody><a:bodyPr wrap="none" lIns="0" tIns="0" rIns="0" bIns="0" rtlCol="0"><a:spAutoFit/></a:bodyPr><a:lstStyle/><a:p><a:pPr indent="-274320" algn="r"><a:spcAft><a:spcPts val="900"/></a:spcAft></a:pPr><a:r><a:rPr lang="en-GB" sz="800" noProof="1"><a:solidFill><a:schemeClr val="tx1"/></a:solidFill><a:latin typeface="Arial" panose="020B0604020202020204" pitchFamily="34" charset="0"/><a:cs typeface="Arial" panose="020B0604020202020204" pitchFamily="34" charset="0"/></a:rPr><a:t>9 February 2023</a:t></a:r></a:p></p:txBody></p:sp><p:sp><p:nvSpPr><p:cNvPr id="20" name="PwC"><a:extLst><a:ext uri="{FF2B5EF4-FFF2-40B4-BE49-F238E27FC236}"><a16:creationId xmlns:a16="http://schemas.microsoft.com/office/drawing/2014/main" id="{58F13C59-450E-4023-A06F-17047DBAF550}"/></a:ext></a:extLst></p:cNvPr><p:cNvSpPr/><p:nvPr userDrawn="1"><p:custDataLst><p:tags r:id="rId5"/></p:custDataLst></p:nvPr></p:nvSpPr><p:spPr><a:xfrm><a:off x="457200" y="7324804"/><a:ext cx="233294" cy="123111"/></a:xfrm><a:prstGeom prst="rect"><a:avLst/></a:prstGeom><a:noFill/><a:ln><a:noFill/></a:ln></p:spPr><p:txBody><a:bodyPr wrap="square" lIns="0" tIns="0" rIns="0" bIns="0" rtlCol="0" anchor="b" anchorCtr="0"><a:spAutoFit/></a:bodyPr><a:lstStyle/><a:p><a:pPr lvl="0"/><a:r><a:rPr lang="en-GB" sz="800" dirty="0"><a:solidFill><a:schemeClr val="tx1"/></a:solidFill><a:latin typeface="Arial" panose="020B0604020202020204" pitchFamily="34" charset="0"/><a:cs typeface="Arial" panose="020B0604020202020204" pitchFamily="34" charset="0"/></a:rPr><a:t>PwC</a:t></a:r></a:p></p:txBody></p:sp><p:sp><p:nvSpPr><p:cNvPr id="27" name="Draft stamp"><a:extLst><a:ext uri="{FF2B5EF4-FFF2-40B4-BE49-F238E27FC236}"><a16:creationId xmlns:a16="http://schemas.microsoft.com/office/drawing/2014/main" id="{008829DD-3A41-4CD3-A972-D63AEAC6F9B8}"/></a:ext></a:extLst></p:cNvPr><p:cNvSpPr txBox="1"/><p:nvPr userDrawn="1"><p:custDataLst><p:tags r:id="rId6"/></p:custDataLst></p:nvPr></p:nvSpPr><p:spPr><a:xfrm><a:off x="4096341" y="7324804"/><a:ext cx="222818" cy="123111"/></a:xfrm><a:prstGeom prst="rect"><a:avLst/></a:prstGeom><a:noFill/><a:ln><a:noFill/></a:ln></p:spPr><p:txBody><a:bodyPr wrap="none" lIns="0" tIns="0" rIns="0" bIns="0" rtlCol="0"><a:spAutoFit/></a:bodyPr><a:lstStyle/><a:p><a:pPr algn="l"/><a:r><a:rPr lang="en-GB" sz="800" noProof="1"><a:solidFill><a:schemeClr val="tx1"/></a:solidFill></a:rPr><a:t>Draft</a:t></a:r></a:p></p:txBody></p:sp><p:sp><p:nvSpPr><p:cNvPr id="29" name="Page Number"><a:extLst><a:ext uri="{FF2B5EF4-FFF2-40B4-BE49-F238E27FC236}"><a16:creationId xmlns:a16="http://schemas.microsoft.com/office/drawing/2014/main" id="{ACB3A705-2339-414D-A765-090F513B72C1}"/></a:ext></a:extLst></p:cNvPr><p:cNvSpPr txBox="1"/><p:nvPr userDrawn="1"><p:custDataLst><p:tags r:id="rId7"/></p:custDataLst></p:nvPr></p:nvSpPr><p:spPr><a:xfrm><a:off x="7927848" y="7324804"/><a:ext cx="1673352" cy="123111"/></a:xfrm><a:prstGeom prst="rect"><a:avLst/></a:prstGeom><a:noFill/></p:spPr><p:txBody><a:bodyPr wrap="none" lIns="0" tIns="0" rIns="0" bIns="0" rtlCol="0"><a:noAutofit/></a:bodyPr><a:lstStyle/><a:p><a:pPr algn="r"><a:lnSpc><a:spcPts val="1000"/></a:lnSpc></a:pPr><a:endParaRPr lang="en-GB" sz="800" noProof="1"><a:solidFill><a:schemeClr val="tx1"/></a:solidFill><a:latin typeface="Arial" panose="020B0604020202020204" pitchFamily="34" charset="0"/><a:cs typeface="Arial" panose="020B0604020202020204" pitchFamily="34" charset="0"/></a:endParaRPr></a:p></p:txBody></p:sp></p:spTree><p:extLst><p:ext uri="{BB962C8B-B14F-4D97-AF65-F5344CB8AC3E}"><p14:creationId xmlns:p14="http://schemas.microsoft.com/office/powerpoint/2010/main" val="109945149"/></p:ext></p:extLst></p:cSld><p:clrMapOvr><a:masterClrMapping/></p:clrMapOvr></p:sldLayout>